{
  "general": {
    "userAgentAdd": "gonative",
    "useWKWebView": true,
    "enableWindowOpen": true,
    "useCrosswalkWebView": false,
    "forceScreenOrientation": "portrait",
    "initialUrl": "https://trade.phoneunlockingguru.co.uk/",
    "appName": "Phone Unlocking Guru",
    "iosBundleId": "com.PUG.app",
    "androidPackageName": "com.pug.app"
  },
  "navigation": {
    "androidPullToRefresh": true,
    "iosPullToRefresh": true,
    "androidShowRefreshButton": false,
    "iosShowRefreshButton": false,
    "deepLinkDomains": [
      "trade.phoneunlockingguru.co.uk"
    ],
    "tabNavigation": {
      "tabSelectionConfig": [
        {
          "id": "1",
          "regex": ""
        }
      ],
      "tabMenus": [
        {
          "id": "1",
          "items": [
            {}
          ]
        }
      ],
      "active": false
    },
    "sidebarNavigation": {
      "menus": [
        {
          "name": "default",
          "items": [
            {
              "label": "Home",
              "url": "https://www.phoneunlockingguru.co.uk/home",
              "subLinks": []
            },
            {
              "label": "Unlocking",
              "url": "https://www.phoneunlockingguru.co.uk/phone-unlock/",
              "subLinks": []
            },
            {
              "label": "Trade/B2B Unlocking",
              "url": "https://trade.phoneunlockingguru.co.uk/phone-unlock/"
            },
            {
              "label": "My Account",
              "url": "https://www.phoneunlockingguru.co.uk/my-account/"
            }
          ],
          "active": false
        },
        {
          "name": "loggedIn",
          "items": [
            {
              "label": "Sample Home",
              "url": "https://www.phoneunlockingguru.co.uk//home",
              "subLinks": []
            },
            {
              "label": "Sample About",
              "url": "https://www.phoneunlockingguru.co.uk//about",
              "subLinks": []
            }
          ],
          "active": false
        }
      ],
      "menuSelectionConfig": {
        "testURL": null,
        "redirectLocations": [
          {
            "regex": null,
            "menuName": "default",
            "loggedIn": false
          },
          {
            "regex": ".*",
            "menuName": "default",
            "loggedIn": true
          }
        ]
      }
    },
    "navigationLevels": {
      "levels": [
        {}
      ]
    },
    "navigationTitles": {
      "titles": [
        {}
      ]
    },
    "regexInternalExternal": {
      "rules": [
        {
          "regex": "^(?!https?://).*",
          "internal": true
        },
        {
          "regex": "https?://([-\\w]+\\.)*facebook\\.com/login.php.*",
          "internal": true
        },
        {
          "regex": "https?://([-\\w]+\\.)*facebook\\.com/dialog.*",
          "internal": true
        },
        {
          "regex": "https?://([-\\w]+\\.)*facebook\\.com/v1\\.0/.*",
          "internal": true
        },
        {
          "regex": "https?://([-\\w]+\\.)*facebook\\.com/oauth.*",
          "internal": true
        },
        {
          "regex": "https?://([-\\w]+\\.)*facebook\\.com/v2\\.0/.*",
          "internal": true
        },
        {
          "regex": "https?://([-\\w]+\\.)*facebook\\.com/checkpoint.*",
          "internal": true
        },
        {
          "regex": "https?://([-\\w]+\\.)*facebook\\.com.*",
          "internal": true
        },
        {
          "regex": "https?://([-\\w]+\\.)*plus\\.google\\.com/share.*",
          "internal": false
        },
        {
          "regex": "https?://([-\\w]+\\.)*twitter\\.com/.*",
          "internal": false
        },
        {
          "regex": "https?://([-\\w]+\\.)*instagram\\.com/.*",
          "internal": false
        },
        {
          "regex": "https?://maps\\.google\\.com.*",
          "internal": false
        },
        {
          "regex": "https?://([-\\w]+\\.)*linkedin\\.com/.*",
          "internal": false
        },
        {
          "regex": "https?://([-\\w]+\\.)*google\\.com/maps/search/.*",
          "internal": false
        },
        {
          "regex": ".*",
          "internal": true
        }
      ],
      "active": true
    },
    "toolbarNavigation": {
      "visibility": "anyItemEnabled",
      "items": [
        {
          "system": "back"
        }
      ]
    }
  },
  "styling": {
    "icon": "https://gonativeio.s3.amazonaws.com/uploads/cvtrg0fzburkm_1587834958262.png",
    "iosHeaderImage": "images/logo1.png",
    "showActionBar": false,
    "showNavigationBar": false,
    "iosSidebarFont": "Default",
    "androidHideTitleInActionBar": false,
    "navigationTitleImage": false,
    "iosTheme": "default",
    "androidTheme": "light",
    "menuAnimationDuration": 0.15,
    "transitionInteractiveDelayMax": 0.2,
    "hideWebviewAlpha": 0.5,
    "disableAnimations": false,
    "androidShowSplash": true,
    "androidSidebarBackgroundColor": "#FFFFFF",
    "androidSidebarForegroundColor": "#777777",
    "androidActionBarBackgroundColor": "#bdbdbd",
    "androidActionBarForegroundColor": "#000000",
    "androidPullToRefreshColor": "#777777",
    "androidAccentColor": "#009688",
    "androidSidebarSeparatorColor": "#585858",
    "androidTabBarBackgroundColor": "#bdbdbd",
    "androidTabBarTextColor": "#000000",
    "androidTabBarIndicatorColor": "#000000",
    "androidLaunchImages": {
      "mdpi": "https://s3.amazonaws.com/gonativeio/images_generated/1587835313226_0gmhjr8jfjagy_180x180.9.png",
      "hdpi": "https://s3.amazonaws.com/gonativeio/images_generated/1587835313226_bv3qwyu5xck6g_270x270.9.png",
      "xhdpi": "https://s3.amazonaws.com/gonativeio/images_generated/1587835313227_q0wwu0tjn43q6_360x360.9.png",
      "xxhdpi": "https://s3.amazonaws.com/gonativeio/images_generated/1587835313227_c9dm7vr4wdwgr_540x540.9.png",
      "xxxhdpi": "https://s3.amazonaws.com/gonativeio/images_generated/1587835313227_5vvpht8ahgnay_720x720.9.png"
    },
    "iosLaunchScreen": {
      "backgroundColor": "#FFFFFF",
      "backgroundImage": "https://s3.amazonaws.com/gonativeio/public/ios_launch_screen_background_default_FFFFFF_1_2x2.png",
      "centerImage": "https://s3.amazonaws.com/gonativeio/images_generated/1587835170935_cdanfgxh2wzg0.png"
    },
    "androidStatusBarBackgroundColor": "#1E5090"
  },
  "forms": {
    "search": {},
    "loginConfig": {
      "formSelector": null,
      "loginIsFirstPage": false
    },
    "signupConfig": {
      "active": false,
      "formSelector": null
    }
  },
  "permissions": {
    "usesGeolocation": false,
    "androidDownloadToPublicStorage": false,
    "enableWebRTC": false
  },
  "performance": {
    "webviewPools": [
      {
        "urls": [
          {
            "disown": "reload"
          }
        ]
      }
    ]
  },
  "publishing": {},
  "services": {
    "push": {
      "active": false
    },
    "analytics": {
      "active": false
    },
    "parse": {
      "active": false,
      "pushEnabled": false
    },
    "facebook": {
      "active": false
    },
    "oneSignal": {
      "active": false,
      "notificationExtension": false
    },
    "registration": {
      "active": false,
      "endpoints": [
        {
          "url": null,
          "urlRegex": null,
          "dataType": [
            "parse",
            "oneSignal",
            "xtremepush"
          ]
        }
      ]
    }
  }
}
